[
    {
        "id": 1,
        "company": "Mishra Dhatu Nigam Ltd",
        "client": "Undisclosed Client",
        "type": "Order Received",
        "description": "Announcement under Regulation 30 (LODR)-Award_of_Order_Receipt_of_Order Information regarding receipt of an Order. MIDHANI secured Rs.121.75 Cr",
        "amount_cr": "Rs.121.75 Cr",
        "order_book_cr": "Rs. 30419 Cr",
        "date": "2025-12-18",
        "category": "General",
        "pdf_link": "https://www.bseindia.com/stockinfo/AnnPdfOpen.aspx?Pname=f3579061-c738-43ce-9076-34df430f2734.pdf",
        "sentiment": "positive"
    },
    {
        "id": 2,
        "company": "Narayana Hrudayalaya Ltd",
        "client": "Undisclosed Client",
        "type": "Order Received",
        "description": "proposed to be held on January 19, 2026 at 2 P.M. pursuant to the Directions of Hon''ble National Company Law Tribunal, Bengaluru Bench NCLT-ordered",
        "amount_cr": "",
        "order_book_cr": "Rs. 11316 Cr",
        "date": "2025-12-18",
        "category": "General",
        "pdf_link": "https://www.bseindia.com/stockinfo/AnnPdfOpen.aspx?Pname=0b8b5a7a-ecd8-43b6-a090-3119a65a45a9.pdf",
        "sentiment": "positive"
    },
    {
        "id": 3,
        "company": "Refex Industries Ltd",
        "client": "Undisclosed Client",
        "type": "Order Received",
        "description": "Announcement under Regulation 30 (LODR)-Award_of_Order_Receipt_of_Order Disclosure under Regulation 30 of SEBI (LODR) Regulations 2015 - Bagging of",
        "amount_cr": "",
        "order_book_cr": "Rs. 40014 Cr",
        "date": "2025-12-18",
        "category": "General",
        "pdf_link": "https://www.bseindia.com/stockinfo/AnnPdfOpen.aspx?Pname=86161779-6b3f-4187-a7d1-bf767dd480ba.pdf",
        "sentiment": "positive"
    },
    {
        "id": 4,
        "company": "Amines & Plasticizers Ltd",
        "client": "Undisclosed Client",
        "type": "Order Received",
        "description": "reference to significant movement in price, in order to ensure that investors have latest relevant information about the company and to inform the",
        "amount_cr": "",
        "order_book_cr": "Rs. 36840 Cr",
        "date": "2025-12-18",
        "category": "General",
        "pdf_link": "/company/id/167/",
        "sentiment": "positive"
    },
    {
        "id": 5,
        "company": "K K Silk Mills Ltd",
        "client": "Undisclosed Client",
        "type": "Order Received",
        "description": "significant movement in price in order to ensure that investors have latest relevant information about the company and to inform the market so that",
        "amount_cr": "",
        "order_book_cr": "Rs. 44489 Cr",
        "date": "2025-12-18",
        "category": "General",
        "pdf_link": "/company/id/1285779/",
        "sentiment": "positive"
    },
    {
        "id": 6,
        "company": "Valson Industries Ltd",
        "client": "Undisclosed Client",
        "type": "Order Received",
        "description": "to significant movement in price, in order to ensure that investors have latest relevant information about the company and to inform the market so",
        "amount_cr": "",
        "order_book_cr": "Rs. 72830 Cr",
        "date": "2025-12-18",
        "category": "General",
        "pdf_link": "/company/id/3597/",
        "sentiment": "positive"
    },
    {
        "id": 7,
        "company": "Sanrhea Technical Textile Ltd",
        "client": "Undisclosed Client",
        "type": "Order Received",
        "description": "2025, with reference to significant movement in price, in order to ensure that investors have latest relevant information about the company and to",
        "amount_cr": "",
        "order_book_cr": "Rs. 7466 Cr",
        "date": "2025-12-18",
        "category": "General",
        "pdf_link": "/company/id/1972/",
        "sentiment": "positive"
    },
    {
        "id": 8,
        "company": "Ampvolts Ltd",
        "client": "Undisclosed Client",
        "type": "Order Received",
        "description": "movement in price, in order to ensure that investors have latest relevant information about the company and to inform the market so that the interest",
        "amount_cr": "",
        "order_book_cr": "Rs. 56634 Cr",
        "date": "2025-12-18",
        "category": "General",
        "pdf_link": "/company/id/463832/",
        "sentiment": "positive"
    },
    {
        "id": 9,
        "company": "Antony Waste Handling Cell Ltd",
        "client": "Antony Waste",
        "type": "Order Received",
        "description": "approved merger of AG Enviro into Antony Waste; appointed date April 1, 2025; order dated Dec 18, 2025",
        "amount_cr": "",
        "order_book_cr": "Rs. 77787 Cr",
        "date": "2025-12-18",
        "category": "General",
        "pdf_link": "https://www.bseindia.com/stockinfo/AnnPdfOpen.aspx?Pname=969eaeb5-1b4b-4d95-b4bf-5ab2028f15c4.pdf",
        "sentiment": "positive"
    },
    {
        "id": 10,
        "company": "Birla Corporation Ltd",
        "client": "Undisclosed Client",
        "type": "Order Received",
        "description": "Order dated 17th December, 2025 has disposed of GA/1/2023 in CS/186/2023 observing that Interim Order passed on 5th September, 2023 had expired and as",
        "amount_cr": "",
        "order_book_cr": "Rs. 21616 Cr",
        "date": "2025-12-18",
        "category": "General",
        "pdf_link": "https://www.bseindia.com/stockinfo/AnnPdfOpen.aspx?Pname=fd623f6e-5877-4984-b9f5-68a49cd0ee9b.pdf",
        "sentiment": "positive"
    },
    {
        "id": 11,
        "company": "BLS International Services Ltd",
        "client": "Undisclosed Client",
        "type": "Order Received",
        "description": "debarment order passed by the MEA. Consequently, the debarment imposed on the Company pursuant to the said order stands quashed. Delhi High Court",
        "amount_cr": "",
        "order_book_cr": "Rs. 25993 Cr",
        "date": "2025-12-18",
        "category": "General",
        "pdf_link": "https://www.bseindia.com/stockinfo/AnnPdfOpen.aspx?Pname=5b8435da-4d99-46fe-984f-a9c2bdd1422e.pdf",
        "sentiment": "positive"
    },
    {
        "id": 12,
        "company": "Cello World Ltd",
        "client": "Undisclosed Client",
        "type": "Order Received",
        "description": "Intimation Under Regulation 30 Order-In-Original Passed By GST Authorities (In Continuation Of Earlier Disclosure Dated June 24, 2025) Intimation",
        "amount_cr": "",
        "order_book_cr": "Rs. 45019 Cr",
        "date": "2025-12-18",
        "category": "General",
        "pdf_link": "https://www.bseindia.com/stockinfo/AnnPdfOpen.aspx?Pname=5d2518b6-b326-40aa-bfd0-68b4f7ea4897.pdf",
        "sentiment": "positive"
    },
    {
        "id": 13,
        "company": "Precision Electronics Ltd",
        "client": "Undisclosed Client",
        "type": "Order Received",
        "description": "Announcement under Regulation 30 (LODR)-Award_of_Order_Receipt_of_Order Disclosure for Award of Order Domestic defense machining order worth Rs.2.16",
        "amount_cr": "Rs.2.16",
        "order_book_cr": "Rs. 61249 Cr",
        "date": "2025-12-18",
        "category": "Defense",
        "pdf_link": "https://www.bseindia.com/stockinfo/AnnPdfOpen.aspx?Pname=6e7b78e0-0f1a-4936-bdab-cfe364ba179d.pdf",
        "sentiment": "positive"
    },
    {
        "id": 14,
        "company": "Panasonic Energy India Company Ltd",
        "client": "Undisclosed Client",
        "type": "Order Received",
        "description": "Announcement under Regulation 30 (LODR)-Award_of_Order_Receipt_of_Order This is to inform you that the company had received a order from the office",
        "amount_cr": "",
        "order_book_cr": "Rs. 65130 Cr",
        "date": "2025-12-18",
        "category": "General",
        "pdf_link": "https://www.bseindia.com/stockinfo/AnnPdfOpen.aspx?Pname=d34be848-50f6-4647-8aca-dc375a90f928.pdf",
        "sentiment": "positive"
    },
    {
        "id": 15,
        "company": "Artefact Projects Ltd",
        "client": "Undisclosed Client",
        "type": "Order Received",
        "description": "Announcement under Regulation 30 (LODR)-Award_of_Order_Receipt_of_Order letter of Award Received LoA: Rs.5,96,24,928 consultancy for NH-343",
        "amount_cr": "Rs.5,96,24,928 ",
        "order_book_cr": "Rs. 27712 Cr",
        "date": "2025-12-18",
        "category": "General",
        "pdf_link": "https://www.bseindia.com/stockinfo/AnnPdfOpen.aspx?Pname=5f47cf61-77f3-43eb-bb84-2d23b04abfdc.pdf",
        "sentiment": "positive"
    },
    {
        "id": 16,
        "company": "Dhanuka Agritech Ltd",
        "client": "Undisclosed Client",
        "type": "Order Received",
        "description": "Announcement Under Regulation 30 Of SEBI LODR- Order Received From State Goods & Services Department, Government Of Rajasthan, Jaipur Order received",
        "amount_cr": "",
        "order_book_cr": "Rs. 56469 Cr",
        "date": "2025-12-18",
        "category": "General",
        "pdf_link": "https://www.bseindia.com/stockinfo/AnnPdfOpen.aspx?Pname=117e2e75-5156-4f7c-a640-f96e6bc69a5c.pdf",
        "sentiment": "positive"
    },
    {
        "id": 17,
        "company": "IndusInd Bank Ltd",
        "client": "Undisclosed Client",
        "type": "Order Received",
        "description": "IndusInd Bank Under SFIO Scanner as MCA Orders Probe Citing Public Interest\" appearing on https:// www.news18.com dated December 18, 2025 (Link",
        "amount_cr": "",
        "order_book_cr": "Rs. 54016 Cr",
        "date": "2025-12-18",
        "category": "General",
        "pdf_link": "/company/id/1480/",
        "sentiment": "positive"
    },
    {
        "id": 18,
        "company": "GPT Infraprojects Ltd",
        "client": "Undisclosed Client",
        "type": "Order Received",
        "description": "Announcement under Regulation 30 (LODR)-Award_of_Order_Receipt_of_Order Please find press release for order bagged by the Company worth Rs. 1804.48",
        "amount_cr": "Rs. 1804.48",
        "order_book_cr": "Rs. 54692 Cr",
        "date": "2025-12-18",
        "category": "General",
        "pdf_link": "https://www.bseindia.com/stockinfo/AnnPdfOpen.aspx?Pname=c6561f6b-e2ce-4768-95ed-d9bb97833bec.pdf",
        "sentiment": "positive"
    },
    {
        "id": 19,
        "company": "Sameera Agro and Infra Ltd",
        "client": "Undisclosed Client",
        "type": "Order Received",
        "description": "Price movement Significant movement in price has been observed in Sameera Agro And Infra Limited. The Exchange, in order to ensure that investors",
        "amount_cr": "",
        "order_book_cr": "Rs. 71040 Cr",
        "date": "2025-12-18",
        "category": "General",
        "pdf_link": "https://www1.nseindia.com/sme/marketinfo/corporates/announcements/announcementDetails.jsp?seqId=106471441",
        "sentiment": "positive"
    },
    {
        "id": 20,
        "company": "Niraj Cement Structurals Ltd",
        "client": "Undisclosed Client",
        "type": "Order Received",
        "description": "Announcement under Regulation 30 (LODR)-Award_of_Order_Receipt_of_Order Announcement under Regulation 30 of SEBI LODR 2015",
        "amount_cr": "",
        "order_book_cr": "Rs. 12071 Cr",
        "date": "2025-12-18",
        "category": "General",
        "pdf_link": "https://www.bseindia.com/stockinfo/AnnPdfOpen.aspx?Pname=dd1a93f4-02c7-43bc-9e6c-381374d4ebc7.pdf",
        "sentiment": "positive"
    },
    {
        "id": 21,
        "company": "Indigo Paints Ltd",
        "client": "Undisclosed Client",
        "type": "Order Received",
        "description": "Announcement Under Reg 30 (LODR) Announcement Under Reg 30 (LODR) - Order passed by the Commissioner of Central Goods & Service Tax, Ahmedabad",
        "amount_cr": "",
        "order_book_cr": "Rs. 34043 Cr",
        "date": "2025-12-18",
        "category": "General",
        "pdf_link": "https://www.bseindia.com/stockinfo/AnnPdfOpen.aspx?Pname=73a6e03f-12ce-4629-97b0-88f41d2c91ad.pdf",
        "sentiment": "positive"
    },
    {
        "id": 22,
        "company": "A B Infrabuild Ltd",
        "client": "Undisclosed Client",
        "type": "Order Received",
        "description": "Announcement under Regulation 30 (LODR)-Award_of_Order_Receipt_of_Order Intimation of allotment of Order",
        "amount_cr": "",
        "order_book_cr": "Rs. 41788 Cr",
        "date": "2025-12-18",
        "category": "General",
        "pdf_link": "https://www.bseindia.com/stockinfo/AnnPdfOpen.aspx?Pname=ae0fea6b-ddef-44b4-a7fa-8ea23d57a3af.pdf",
        "sentiment": "positive"
    },
    {
        "id": 23,
        "company": "United Heat Transfer Ltd",
        "client": "Undisclosed Client",
        "type": "Order Received",
        "description": "Bagging/Receiving of orders/contracts United Heat Transfer Limited has informed the Exchange about Bagging/Receiving of orders/contracts Purchase",
        "amount_cr": "",
        "order_book_cr": "Rs. 56812 Cr",
        "date": "2025-12-18",
        "category": "General",
        "pdf_link": "https://nsearchives.nseindia.com/corporate/UNITEDHEAT_18122025172144_UHTL_Reporting_of_Orders.pdf",
        "sentiment": "positive"
    },
    {
        "id": 24,
        "company": "SEAMEC Ltd",
        "client": "Adsun for diving services",
        "type": "Order Received",
        "description": "Announcement under Regulation 30 (LODR)-Award_of_Order_Receipt_of_Order Please find as attached Awarded USD 3.25M LOA to Adsun for diving services",
        "amount_cr": "",
        "order_book_cr": "Rs. 49929 Cr",
        "date": "2025-12-18",
        "category": "General",
        "pdf_link": "https://www.bseindia.com/stockinfo/AnnPdfOpen.aspx?Pname=84f97f5d-a40e-46b0-9a02-e4e7cb925bec.pdf",
        "sentiment": "positive"
    },
    {
        "id": 25,
        "company": "Kabra Commercial Ltd",
        "client": "Undisclosed Client",
        "type": "Order Received",
        "description": "Announcement under Regulation 30 (LODR)-Award_of_Order_Receipt_of_Order This is to inform that demat account of the Company has been freeze by the",
        "amount_cr": "",
        "order_book_cr": "Rs. 46202 Cr",
        "date": "2025-12-18",
        "category": "General",
        "pdf_link": "https://www.bseindia.com/stockinfo/AnnPdfOpen.aspx?Pname=e060a73d-39e4-413e-b7d9-159cba247940.pdf",
        "sentiment": "positive"
    },
    {
        "id": 26,
        "company": "NIS Management Ltd",
        "client": "Irrigation & Waterways",
        "type": "Order Received",
        "description": "Announcement under Regulation 30 (LODR)-Award_of_Order_Receipt_of_Order Company has been awarded with a work order from Irrigation & Waterways",
        "amount_cr": "",
        "order_book_cr": "Rs. 57274 Cr",
        "date": "2025-12-18",
        "category": "General",
        "pdf_link": "https://www.bseindia.com/stockinfo/AnnPdfOpen.aspx?Pname=532fa724-e171-4d0b-9349-f0013f20e329.pdf",
        "sentiment": "positive"
    },
    {
        "id": 27,
        "company": "Piotex Industries Ltd",
        "client": "Undisclosed Client",
        "type": "Regulatory Order/Penalty",
        "description": "Update On Announcement Dated 17.12.2025 Pls refer PDF file Piotex clarifies Income Tax Demand Order dated 02-Dec-2025 received 17-Dec-2025",
        "amount_cr": "",
        "order_book_cr": "Rs. 55807 Cr",
        "date": "2025-12-18",
        "category": "General",
        "pdf_link": "https://www.bseindia.com/stockinfo/AnnPdfOpen.aspx?Pname=cbef8774-6809-46ec-ac54-38e7c634e1c2.pdf",
        "sentiment": "negative"
    },
    {
        "id": 28,
        "company": "Blue Chip India Ltd",
        "client": "Undisclosed Client",
        "type": "Order Received",
        "description": "Board of Directors will be held on Tuesday 23rd December, 2025, in order to transact the following business: 1. To consider the reduction of share",
        "amount_cr": "",
        "order_book_cr": "Rs. 53421 Cr",
        "date": "2025-12-18",
        "category": "General",
        "pdf_link": "https://www.bseindia.com/stockinfo/AnnPdfOpen.aspx?Pname=2cca4bf2-e1b8-484b-a7fd-bda5e53f2220.pdf",
        "sentiment": "positive"
    },
    {
        "id": 29,
        "company": "BIGBLOC Construction Ltd",
        "client": "Larsen",
        "type": "Order Received",
        "description": "Announcement under Regulation 30 (LODR)-Award_of_Order_Receipt_of_Order Intimation of receipt of Purchase Order attached Purchase order from Larsen",
        "amount_cr": "",
        "order_book_cr": "Rs. 9609 Cr",
        "date": "2025-12-18",
        "category": "General",
        "pdf_link": "https://www.bseindia.com/stockinfo/AnnPdfOpen.aspx?Pname=f38d17b9-3c35-4786-a944-4aa109b7b3b4.pdf",
        "sentiment": "positive"
    },
    {
        "id": 30,
        "company": "JFL Life Sciences Ltd",
        "client": "Nazir Abdali Limited",
        "type": "Order Received",
        "description": "General Updates Jfl Life Sciences Limited has informed the Exchange about an order received from Nazir Abdali Limited, Afghanistan. Received USD 204",
        "amount_cr": "",
        "order_book_cr": "Rs. 37641 Cr",
        "date": "2025-12-18",
        "category": "General",
        "pdf_link": "https://nsearchives.nseindia.com/corporate/JFL_18122025145146_JFL_Regulation_30_order_18-12-2025_Signed.pdf",
        "sentiment": "positive"
    },
    {
        "id": 31,
        "company": "Manglam Infra & Engineering Ltd",
        "client": "Undisclosed Client",
        "type": "Order Received",
        "description": "Bagging/Receiving of orders/contracts Manglam Infra & Engineering Limited has informed the Exchange about Bagging/Receiving of orders/contracts",
        "amount_cr": "",
        "order_book_cr": "Rs. 30011 Cr",
        "date": "2025-12-18",
        "category": "General",
        "pdf_link": "https://nsearchives.nseindia.com/corporate/MANGLAMINFRA_18122025142047_varanasi_nse.pdf",
        "sentiment": "positive"
    },
    {
        "id": 32,
        "company": "CFF Fluid Control Ltd",
        "client": "Undisclosed Client",
        "type": "Order Received",
        "description": "Announcement under Regulation 30 (LODR)-Award_of_Order_Receipt_of_Order Receipt of Purchase Order Intimation under Regulation 30 of SEBI (Listing",
        "amount_cr": "",
        "order_book_cr": "Rs. 58801 Cr",
        "date": "2025-12-18",
        "category": "General",
        "pdf_link": "https://www.bseindia.com/stockinfo/AnnPdfOpen.aspx?Pname=836d3b15-e9ce-4bf7-bdf5-3a2cfbf16ead.pdf",
        "sentiment": "positive"
    },
    {
        "id": 33,
        "company": "Mawana Sugars Ltd",
        "client": "Undisclosed Client",
        "type": "Order Received",
        "description": "Ashok Kumar Shukla, Company Secretary. In this regard, we wish to inform you that Adjudication Officer of SEBI , vide its order dated December 17",
        "amount_cr": "",
        "order_book_cr": "Rs. 44546 Cr",
        "date": "2025-12-18",
        "category": "General",
        "pdf_link": "https://www.bseindia.com/stockinfo/AnnPdfOpen.aspx?Pname=b34b8340-86d4-45a7-a9ff-7e249187be22.pdf",
        "sentiment": "positive"
    },
    {
        "id": 34,
        "company": "HBL Engineering Ltd",
        "client": "Undisclosed Client",
        "type": "Order Received",
        "description": "Information To Stakeholders Information to stakeholders 2024 2,200-unit order: 1,659 delivered, 541 cancelled; ~18,429 units expected next year",
        "amount_cr": "rs 2024 ",
        "order_book_cr": "Rs. 75151 Cr",
        "date": "2025-12-18",
        "category": "General",
        "pdf_link": "https://www.bseindia.com/stockinfo/AnnPdfOpen.aspx?Pname=99c3a839-cf5f-4f52-8527-6771b601abf5.pdf",
        "sentiment": "positive"
    },
    {
        "id": 35,
        "company": "Voltas Ltd",
        "client": "Undisclosed Client",
        "type": "Order Received",
        "description": "under Regulation 30 of Listing Regulations - Receipt of orders from the GST authority Three GST orders (17-Dec-2025) demanding \u20b94.35 crore tax and",
        "amount_cr": "",
        "order_book_cr": "Rs. 56550 Cr",
        "date": "2025-12-18",
        "category": "General",
        "pdf_link": "https://www.bseindia.com/stockinfo/AnnPdfOpen.aspx?Pname=6c06f91d-849b-4ef9-a8fb-c352b40f17bc.pdf",
        "sentiment": "positive"
    },
    {
        "id": 36,
        "company": "Vinyas Innovative Technologies Ltd",
        "client": "Undisclosed Client",
        "type": "Order Received",
        "description": "Bagging/Receiving of orders/contracts Vinyas Innovative Technologies Limited has informed the Exchange about Bagging/Receiving of orders/contracts",
        "amount_cr": "",
        "order_book_cr": "Rs. 77331 Cr",
        "date": "2025-12-18",
        "category": "Technology",
        "pdf_link": "https://nsearchives.nseindia.com/corporate/VINYAS_18122025112237_Intimation_SIGNED.pdf",
        "sentiment": "positive"
    },
    {
        "id": 37,
        "company": "MTAR Technologies Ltd",
        "client": "Undisclosed Client",
        "type": "Order Received",
        "description": "Announcement under Regulation 30 (LODR)-Award_of_Order_Receipt_of_Order Receipt of orders worth Rs. 310 Crores from new customer",
        "amount_cr": "Rs. 310 Crore",
        "order_book_cr": "Rs. 7336 Cr",
        "date": "2025-12-18",
        "category": "General",
        "pdf_link": "https://www.bseindia.com/stockinfo/AnnPdfOpen.aspx?Pname=84670d37-9005-4734-af6c-631f17ad38a4.pdf",
        "sentiment": "positive"
    },
    {
        "id": 38,
        "company": "BIGBLOC Construction Ltd",
        "client": "Undisclosed Client",
        "type": "Order Received",
        "description": "base with repeat orders from leading developers such as L&T Realty and Lodha ESG: Sustainability at its Core Visit Our Real Time ESG Disclosure",
        "amount_cr": "",
        "order_book_cr": "Rs. 31756 Cr",
        "date": "2025-12-18",
        "category": "General",
        "pdf_link": "https://www.bseindia.com/stockinfo/AnnPdfOpen.aspx?Pname=3fe920e1-063d-47d1-bdfc-502a017e8abb.pdf",
        "sentiment": "positive"
    },
    {
        "id": 39,
        "company": "Cyber Media Research & Services Ltd",
        "client": "Undisclosed Client",
        "type": "Order Received",
        "description": "breakdown of client traction, revenue visibility and order pipeline would be helpful, like business by business? Dhaval Gupta In terms of the",
        "amount_cr": "",
        "order_book_cr": "Rs. 12495 Cr",
        "date": "2025-12-18",
        "category": "General",
        "pdf_link": "https://nsearchives.nseindia.com/corporate/CMRSL_18122025095912_transcript111225.pdf",
        "sentiment": "positive"
    },
    {
        "id": 40,
        "company": "Rulka Electricals Ltd",
        "client": "Undisclosed Client",
        "type": "Order Received",
        "description": "order should be completed, near about 50% should be completed in FY' '26. And what is the order value for the EHV order that we just received",
        "amount_cr": "",
        "order_book_cr": "Rs. 28210 Cr",
        "date": "2025-12-18",
        "category": "General",
        "pdf_link": "https://nsearchives.nseindia.com/corporate/RULKA_18122025150444_LT-38_Investors_Meet_Dec_2025_Transcript.pdf",
        "sentiment": "positive"
    },
    {
        "id": 41,
        "company": "GE Vernova T&D India Ltd",
        "client": "Undisclosed Client",
        "type": "Order Received",
        "description": "Announcement under Regulation 30 (LODR)-Award_of_Order_Receipt_of_Order Intimation of Bagging/Receiving of Order/contracts",
        "amount_cr": "",
        "order_book_cr": "Rs. 19459 Cr",
        "date": "2025-12-17",
        "category": "General",
        "pdf_link": "https://www.bseindia.com/stockinfo/AnnPdfOpen.aspx?Pname=4fa51281-363c-48bc-a921-2e620ee0377e.pdf",
        "sentiment": "positive"
    },
    {
        "id": 42,
        "company": "Hindustan Zinc Ltd",
        "client": "Undisclosed Client",
        "type": "Order Received",
        "description": "the enclosed file Interim order (16 Dec 2025): Rs63.90 lakh compounding for missing DINs (FY2014-15\u20132020-21",
        "amount_cr": "Rs63.90 lakh",
        "order_book_cr": "Rs. 15918 Cr",
        "date": "2025-12-17",
        "category": "General",
        "pdf_link": "https://www.bseindia.com/stockinfo/AnnPdfOpen.aspx?Pname=985c20ae-b83a-443f-a37c-1875a2c2c0c4.pdf",
        "sentiment": "positive"
    },
    {
        "id": 43,
        "company": "Shriram Finance Ltd",
        "client": "Undisclosed Client",
        "type": "Regulatory Order/Penalty",
        "description": "Order Received Order received Lucknow State Tax ordered GST demand Rs2.77cr, interest Rs1.885cr, penalty Rs0.277cr on Dec 16, 2025",
        "amount_cr": "Rs2.77cr",
        "order_book_cr": "Rs. 66403 Cr",
        "date": "2025-12-17",
        "category": "General",
        "pdf_link": "https://www.bseindia.com/stockinfo/AnnPdfOpen.aspx?Pname=cf824e90-44a0-4dc6-be80-ab1278026630.pdf",
        "sentiment": "negative"
    },
    {
        "id": 44,
        "company": "UltraTech Cement Ltd",
        "client": "GST Authority GST order",
        "type": "Order Received",
        "description": "Disclosure W.R.T. Order Passed By GST Authority Disclosure w.r.t. order passed by GST Authority GST order (17-Dec-2025): demand Rs2,587,550",
        "amount_cr": "Rs2,587,550",
        "order_book_cr": "Rs. 44667 Cr",
        "date": "2025-12-17",
        "category": "General",
        "pdf_link": "https://www.bseindia.com/stockinfo/AnnPdfOpen.aspx?Pname=0404aadc-7d25-4220-aff1-dc04ee34345e.pdf",
        "sentiment": "positive"
    },
    {
        "id": 45,
        "company": "Asahi Songwon Colors Ltd",
        "client": "Undisclosed Client",
        "type": "Order Received",
        "description": "reference to significant movement in price, in order to ensure that investors have latest relevant information about the company and to inform the",
        "amount_cr": "",
        "order_book_cr": "Rs. 38176 Cr",
        "date": "2025-12-17",
        "category": "General",
        "pdf_link": "/company/id/267/",
        "sentiment": "positive"
    },
    {
        "id": 46,
        "company": "Tainwala Chemicals & Plastics (India) Ltd",
        "client": "Undisclosed Client",
        "type": "Order Received",
        "description": "India) Ltd on December 17, 2025 with reference to significant movement in price, in order to ensure that investors have latest relevant information",
        "amount_cr": "",
        "order_book_cr": "Rs. 46120 Cr",
        "date": "2025-12-17",
        "category": "General",
        "pdf_link": "/company/id/3340/",
        "sentiment": "positive"
    },
    {
        "id": 47,
        "company": "Dolphin Offshore Enterprises (India) Ltd",
        "client": "Undisclosed Client",
        "type": "Order Received",
        "description": "Ltd on December 17, 2025 with reference to significant movement in price, in order to ensure that investors have latest relevant information about",
        "amount_cr": "",
        "order_book_cr": "Rs. 57581 Cr",
        "date": "2025-12-17",
        "category": "General",
        "pdf_link": "/company/id/846/",
        "sentiment": "positive"
    },
    {
        "id": 48,
        "company": "Shree Rama Multi-Tech Ltd",
        "client": "Undisclosed Client",
        "type": "Order Received",
        "description": "reference to significant movement in price, in order to ensure that investors have latest relevant information about the company and to inform the",
        "amount_cr": "",
        "order_book_cr": "Rs. 46753 Cr",
        "date": "2025-12-17",
        "category": "General",
        "pdf_link": "/company/id/3015/",
        "sentiment": "positive"
    },
    {
        "id": 49,
        "company": "Optimus Finance Ltd",
        "client": "Undisclosed Client",
        "type": "Order Received",
        "description": "significant movement in price, in order to ensure that investors have latest relevant information about the company and to inform the market so that",
        "amount_cr": "",
        "order_book_cr": "Rs. 52786 Cr",
        "date": "2025-12-17",
        "category": "General",
        "pdf_link": "/company/id/100069/",
        "sentiment": "positive"
    },
    {
        "id": 50,
        "company": "KJMC Corporate Advisors (India) Ltd",
        "client": "Undisclosed Client",
        "type": "Order Received",
        "description": "December 17, 2025 with reference to significant movement in price, in order to ensure that investors have latest relevant information about the",
        "amount_cr": "",
        "order_book_cr": "Rs. 62633 Cr",
        "date": "2025-12-17",
        "category": "General",
        "pdf_link": "/company/id/1798/",
        "sentiment": "positive"
    },
    {
        "id": 51,
        "company": "Titagarh Rail Systems Ltd",
        "client": "Undisclosed Client",
        "type": "Order Received",
        "description": "Announcement under Regulation 30 (LODR)-Award_of_Order_Receipt_of_Order We enclose herewith disclosure under Regulation 30 of SEBI (LODR) Regulations",
        "amount_cr": "",
        "order_book_cr": "Rs. 6650 Cr",
        "date": "2025-12-17",
        "category": "General",
        "pdf_link": "https://www.bseindia.com/stockinfo/AnnPdfOpen.aspx?Pname=4b0e86af-0e34-4cdf-bf31-985dc119bb7b.pdf",
        "sentiment": "positive"
    },
    {
        "id": 52,
        "company": "Trishakti Industries Ltd",
        "client": "Undisclosed Client",
        "type": "Order Received",
        "description": "Listing Obligations and Disclosure Requirements) Regulations, 2015 Press Release -Press Release-Strategic MoUs and Equipment Purchase Orders. Signed",
        "amount_cr": "",
        "order_book_cr": "Rs. 65619 Cr",
        "date": "2025-12-17",
        "category": "General",
        "pdf_link": "https://www.bseindia.com/stockinfo/AnnPdfOpen.aspx?Pname=a5999caa-0588-4144-98b2-189c008eb0f9.pdf",
        "sentiment": "positive"
    },
    {
        "id": 53,
        "company": "Shree Marutinandan Tubes Ltd",
        "client": "Undisclosed Client",
        "type": "Order Received",
        "description": "Won INR 15.56 lakh order to supply fire detection items at Vindhyachal, MP; 90-day project",
        "amount_cr": "INR 15.56 lakh",
        "order_book_cr": "Rs. 65462 Cr",
        "date": "2025-12-17",
        "category": "General",
        "pdf_link": "https://www.bseindia.com/stockinfo/AnnPdfOpen.aspx?Pname=52126517-7835-4957-92c0-a7d751639973.pdf",
        "sentiment": "positive"
    },
    {
        "id": 54,
        "company": "Akash Infraprojects Ltd",
        "client": "Undisclosed Client",
        "type": "Order Received",
        "description": "Akash Infra Projects Limited has informed the Exchange about Receipt of Work Order Work order Rs18.21 crore on 17/12/2025 to widen Himmatnagar",
        "amount_cr": "Rs18.21 crore",
        "order_book_cr": "Rs. 32391 Cr",
        "date": "2025-12-17",
        "category": "General",
        "pdf_link": "https://nsearchives.nseindia.com/corporate/AKASH_17122025180825_Akash.pdf",
        "sentiment": "positive"
    },
    {
        "id": 55,
        "company": "SecUR Credentials Ltd",
        "client": "Undisclosed Client",
        "type": "Regulatory Order/Penalty",
        "description": "qualified audit; SEBI interim order; securities suspended; advances \u20b9599.70L; unbilled/related-party issues",
        "amount_cr": "",
        "order_book_cr": "Rs. 68906 Cr",
        "date": "2025-12-17",
        "category": "General",
        "pdf_link": "https://www.bseindia.com/stockinfo/AnnPdfOpen.aspx?Pname=28f87c71-b6ab-4e0a-9bff-ad7742c35176.pdf",
        "sentiment": "negative"
    },
    {
        "id": 56,
        "company": "Texmaco Rail & Engineering Ltd",
        "client": "Undisclosed Client",
        "type": "Order Received",
        "description": "Announcement under Regulation 30 (LODR)-Award_of_Order_Receipt_of_Order Receipt of Order Western Railway awarded Rs.6.70 crore rail electrification",
        "amount_cr": "Rs.6.70 crore",
        "order_book_cr": "Rs. 70035 Cr",
        "date": "2025-12-17",
        "category": "Infrastructure",
        "pdf_link": "https://www.bseindia.com/stockinfo/AnnPdfOpen.aspx?Pname=31eb618f-8c3e-43a2-873c-6488de878cec.pdf",
        "sentiment": "positive"
    },
    {
        "id": 57,
        "company": "BSE Ltd",
        "client": "Undisclosed Client",
        "type": "Regulatory Order/Penalty",
        "description": "BSE Limited has informed the Exchange about Action(s) taken or orders passed. CGST order demands Rs.6.59 crore tax and Rs.0.66 crore penalty (total",
        "amount_cr": "Rs.6.59 crore",
        "order_book_cr": "Rs. 10301 Cr",
        "date": "2025-12-17",
        "category": "General",
        "pdf_link": "https://nsearchives.nseindia.com/corporate/BSE1_17122025173302_NSEintimation.pdf",
        "sentiment": "negative"
    },
    {
        "id": 58,
        "company": "United Drilling Tools Ltd",
        "client": "Undisclosed Client",
        "type": "Order Received",
        "description": "Announcement under Regulation 30 (LODR)-Award_of_Order_Receipt_of_Order GLV order from ONGC Received ONGC order for gas lift valves and side-pocket",
        "amount_cr": "",
        "order_book_cr": "Rs. 76869 Cr",
        "date": "2025-12-17",
        "category": "General",
        "pdf_link": "https://www.bseindia.com/stockinfo/AnnPdfOpen.aspx?Pname=2889e5ce-cfdd-4a22-9eed-b8648e42813c.pdf",
        "sentiment": "positive"
    },
    {
        "id": 59,
        "company": "Thaai Casting Ltd",
        "client": "Undisclosed Client",
        "type": "Order Received",
        "description": "Bagging/Receiving of orders/contracts Thaai Casting Limited has informed the Exchange about Bagging/Receiving of orders/contracts 17 Dec 2025",
        "amount_cr": "",
        "order_book_cr": "Rs. 63193 Cr",
        "date": "2025-12-17",
        "category": "General",
        "pdf_link": "https://nsearchives.nseindia.com/corporate/THAAI_17122025172228_Regulation_30_Order_Bagging_TCL_17_12_2025.pdf",
        "sentiment": "positive"
    },
    {
        "id": 60,
        "company": "Greenchef Appliances Ltd",
        "client": "Undisclosed Client",
        "type": "Regulatory Order/Penalty",
        "description": "Action(s) initiated or orders passed Greenchef Appliances Limited has informed the Exchange about Action(s) initiated or orders passed NSE fined Rs",
        "amount_cr": "",
        "order_book_cr": "Rs. 56472 Cr",
        "date": "2025-12-17",
        "category": "General",
        "pdf_link": "https://nsearchives.nseindia.com/corporate/GREENCHEF_17122025171712_Disclosure_Notice_of_Penalty_Signed.pdf",
        "sentiment": "negative"
    },
    {
        "id": 61,
        "company": "Amara Raja Energy & Mobility Ltd",
        "client": "Undisclosed Client",
        "type": "Regulatory Order/Penalty",
        "description": "Regulation 30 Regulation 30 - Receipt of penalty or order CGST demand Rs1,89,16,214; penalty Rs18,91,621; order dated 17-Dec-2025; company to appeal",
        "amount_cr": "Rs1,89,16,214",
        "order_book_cr": "Rs. 48590 Cr",
        "date": "2025-12-17",
        "category": "General",
        "pdf_link": "https://www.bseindia.com/stockinfo/AnnPdfOpen.aspx?Pname=24fcff8f-4a76-4b80-b22d-d52cfa5a5455.pdf",
        "sentiment": "negative"
    },
    {
        "id": 62,
        "company": "Royal Orchid Hotels Ltd",
        "client": "Undisclosed Client",
        "type": "Order Received",
        "description": "Announcement under Regulation 30 (LODR)-Award_of_Order_Receipt_of_Order Pursuant to Regulation 30 read with Part A of Schedule III of the SEBI LODR",
        "amount_cr": "",
        "order_book_cr": "Rs. 55091 Cr",
        "date": "2025-12-17",
        "category": "General",
        "pdf_link": "https://www.bseindia.com/stockinfo/AnnPdfOpen.aspx?Pname=33d147af-0c3a-42b7-9864-e4bdc281f992.pdf",
        "sentiment": "positive"
    },
    {
        "id": 63,
        "company": "NTPC Ltd",
        "client": "Undisclosed Client",
        "type": "Order Received",
        "description": "Intimation Regarding Receipt Of The Order From The Assistant Commissioner State Tax, Delhi Dislcosure regarding reciept of order from the Assistant",
        "amount_cr": "",
        "order_book_cr": "Rs. 58995 Cr",
        "date": "2025-12-17",
        "category": "General",
        "pdf_link": "https://www.bseindia.com/stockinfo/AnnPdfOpen.aspx?Pname=78edf7aa-750d-4efd-b36e-9072a7546dfd.pdf",
        "sentiment": "positive"
    },
    {
        "id": 64,
        "company": "5paisa Capital Ltd",
        "client": "Undisclosed Client",
        "type": "Order Received",
        "description": "Obligations and Disclosure Requirements) 2015 Received CGST order (Dec 16, 2025) demanding \u20b952,10,113 for alleged ineligible ITC; company to appeal",
        "amount_cr": "",
        "order_book_cr": "Rs. 43535 Cr",
        "date": "2025-12-17",
        "category": "General",
        "pdf_link": "https://www.bseindia.com/stockinfo/AnnPdfOpen.aspx?Pname=911aa7c4-0731-4462-8fdf-8958ab82adc1.pdf",
        "sentiment": "positive"
    },
    {
        "id": 65,
        "company": "Timken India Ltd",
        "client": "Undisclosed Client",
        "type": "Regulatory Order/Penalty",
        "description": "APPEAL AGAINST ORDER PASSED BY DISTRICT CONSUMER DISPUTES REDRESSAL COMMISSION, SHIMLA: UPDATE This is in furtherance to our earlier intimation dated",
        "amount_cr": "",
        "order_book_cr": "Rs. 38319 Cr",
        "date": "2025-12-17",
        "category": "General",
        "pdf_link": "https://www.bseindia.com/stockinfo/AnnPdfOpen.aspx?Pname=d8c01aca-06a1-4159-a5b0-5fdcd389011f.pdf",
        "sentiment": "negative"
    },
    {
        "id": 66,
        "company": "Crompton Greaves Consumer Electricals Ltd",
        "client": "Undisclosed Client",
        "type": "Regulatory Order/Penalty",
        "description": "Disclosure under Regulation 30 of the SEBI (LODR) Regulations, 2015 - Intimation of order passed GST demand INR 1,47,47,140 for Apr 2021\u2013Mar 2022",
        "amount_cr": "INR 1,47,47,140 ",
        "order_book_cr": "Rs. 60072 Cr",
        "date": "2025-12-17",
        "category": "General",
        "pdf_link": "https://www.bseindia.com/stockinfo/AnnPdfOpen.aspx?Pname=e95e0afa-d3f0-4cf6-9e42-4952c0ba24a4.pdf",
        "sentiment": "negative"
    },
    {
        "id": 67,
        "company": "Dabur India Ltd",
        "client": "Undisclosed Client",
        "type": "Regulatory Order/Penalty",
        "description": "on disclosure dated February 5, 2025 Commissioner dismissed Dabur appeal; CGST tax demand Rs.23,06,67,809 plus equal penalty; order received Dec 16",
        "amount_cr": "Rs.23,06,67,809 ",
        "order_book_cr": "Rs. 19779 Cr",
        "date": "2025-12-17",
        "category": "General",
        "pdf_link": "https://www.bseindia.com/stockinfo/AnnPdfOpen.aspx?Pname=07729714-a07f-4b63-b3b6-2dd6607ccc9d.pdf",
        "sentiment": "negative"
    },
    {
        "id": 68,
        "company": "Sharika Enterprises Ltd",
        "client": "LS Cable India Private Limited Rs",
        "type": "Order Received",
        "description": "Announcement under Regulation 30 (LODR)-Award_of_Order_Receipt_of_Order Intimation of Receipt of Order from LS Cable India Private Limited Rs.1,13",
        "amount_cr": "Rs.1,13",
        "order_book_cr": "Rs. 68110 Cr",
        "date": "2025-12-17",
        "category": "General",
        "pdf_link": "https://www.bseindia.com/stockinfo/AnnPdfOpen.aspx?Pname=4a6f793e-2081-49dc-9a97-424720f2391d.pdf",
        "sentiment": "positive"
    },
    {
        "id": 69,
        "company": "Antony Waste Handling Cell Ltd",
        "client": "Material Subsidiary",
        "type": "Order Received",
        "description": "Announcement under Regulation 30 (LODR)-Award_of_Order_Receipt_of_Order Please find intimation w.r.t Receiving of Contracts by Material Subsidiary",
        "amount_cr": "",
        "order_book_cr": "Rs. 59978 Cr",
        "date": "2025-12-17",
        "category": "General",
        "pdf_link": "https://www.bseindia.com/stockinfo/AnnPdfOpen.aspx?Pname=f42d021f-b7e2-4ed7-9851-277f3f408b1a.pdf",
        "sentiment": "positive"
    },
    {
        "id": 70,
        "company": "Shree Securities Ltd",
        "client": "Undisclosed Client",
        "type": "Order Received",
        "description": "Steel Co Private Limited, amounting to \u20b945.82 Crore. However pursuant to order of the NCLT Kolkata Bench, on 28th February 2022, the investment",
        "amount_cr": "",
        "order_book_cr": "Rs. 46605 Cr",
        "date": "2025-12-17",
        "category": "General",
        "pdf_link": "/company/id/1270751/",
        "sentiment": "positive"
    },
    {
        "id": 71,
        "company": "Popular Vehicles & Services Ltd",
        "client": "Undisclosed Client",
        "type": "Order Received",
        "description": "Announcement Under Regulation 30 Of The SEBI (LODR) Regulations, 2015 Regarding The Receipt Of A Demand Order From GST Department Against The",
        "amount_cr": "",
        "order_book_cr": "Rs. 21973 Cr",
        "date": "2025-12-17",
        "category": "General",
        "pdf_link": "https://www.bseindia.com/stockinfo/AnnPdfOpen.aspx?Pname=1c558f46-0168-4a0c-9fbb-d1ce6a265f05.pdf",
        "sentiment": "positive"
    },
    {
        "id": 72,
        "company": "Fertilizers & Chemicals Travancore Ltd",
        "client": "Undisclosed Client",
        "type": "Order Received",
        "description": "Significant increase in volume has been observed in Fertilizers and Chemicals Travancore Limited. The Exchange, in order to ensure that investors have",
        "amount_cr": "",
        "order_book_cr": "Rs. 8663 Cr",
        "date": "2025-12-17",
        "category": "General",
        "pdf_link": "https://nsearchives.nseindia.com/corporate/FACT_17122025151653_CS-HO-RO-274.pdf",
        "sentiment": "positive"
    },
    {
        "id": 73,
        "company": "Cords Cable Industries Ltd",
        "client": "Undisclosed Client",
        "type": "Order Received",
        "description": "Regulations, 2015, we would like to inform the stock exchanges that the company has received an order in original No. 48/GST/BHD-TIJARA/25-26 dated 15",
        "amount_cr": "",
        "order_book_cr": "Rs. 77786 Cr",
        "date": "2025-12-17",
        "category": "General",
        "pdf_link": "https://www.bseindia.com/stockinfo/AnnPdfOpen.aspx?Pname=e8bdef88-7db8-41f9-a54f-b172f740ac57.pdf",
        "sentiment": "positive"
    },
    {
        "id": 74,
        "company": "SML Mahindra Ltd",
        "client": "Undisclosed Client",
        "type": "Regulatory Order/Penalty",
        "description": "aside ROC order dated 21.08.2024; Rs.2.0 lacs penalty cancelled",
        "amount_cr": "Rs.2.0 ",
        "order_book_cr": "Rs. 48690 Cr",
        "date": "2025-12-17",
        "category": "General",
        "pdf_link": "https://www.bseindia.com/stockinfo/AnnPdfOpen.aspx?Pname=cf67f692-b53f-4f9c-8d7a-7f019753d7dc.pdf",
        "sentiment": "negative"
    },
    {
        "id": 75,
        "company": "Samay Project Services Ltd",
        "client": "Undisclosed Client",
        "type": "Order Received",
        "description": "Bagging/Receiving of orders/contracts Samay Project Services Limited has informed the Exchange about Bagging/Receiving of orders/contracts",
        "amount_cr": "",
        "order_book_cr": "Rs. 27552 Cr",
        "date": "2025-12-17",
        "category": "General",
        "pdf_link": "https://nsearchives.nseindia.com/corporate/SAMAY_17122025143237_NSE_intimation_17122025.pdf",
        "sentiment": "positive"
    },
    {
        "id": 76,
        "company": "Swastik Pipe Ltd",
        "client": "Undisclosed Client",
        "type": "Order Received",
        "description": "Action(s) initiated or orders passed Swastik Pipe Limited has informed the Exchange about Action(s) initiated or orders passed",
        "amount_cr": "",
        "order_book_cr": "Rs. 74261 Cr",
        "date": "2025-12-17",
        "category": "General",
        "pdf_link": "https://nsearchives.nseindia.com/corporate/SWASTIKPIPE_17122025142123_NSE_Reply.pdf",
        "sentiment": "positive"
    },
    {
        "id": 77,
        "company": "V.L.Infraprojects Ltd",
        "client": "Undisclosed Client",
        "type": "Order Received",
        "description": "Bagging/Receiving of orders/contracts V.L.Infraprojects Limited has informed the Exchange about Bagging/Receiving of orders/contracts Received Rs.42",
        "amount_cr": "Rs.42",
        "order_book_cr": "Rs. 79977 Cr",
        "date": "2025-12-17",
        "category": "General",
        "pdf_link": "https://nsearchives.nseindia.com/corporate/VLINFRA_17122025140106_WORKORDER.pdf",
        "sentiment": "positive"
    },
    {
        "id": 78,
        "company": "Dynamic Services & Security Ltd",
        "client": "Undisclosed Client",
        "type": "Order Received",
        "description": "Awarding of order(s)/contract(s) Dynamic Services & Security Limited has informed the Exchange about Awarding of order(s)/contract(s) to subsidiary",
        "amount_cr": "",
        "order_book_cr": "Rs. 50052 Cr",
        "date": "2025-12-17",
        "category": "General",
        "pdf_link": "https://nsearchives.nseindia.com/corporate/DYNAMIC_17122025135608_Intimation.pdf",
        "sentiment": "positive"
    },
    {
        "id": 79,
        "company": "Steel City Securities Ltd",
        "client": "Undisclosed Client",
        "type": "Order Received",
        "description": "Steel City Securities Limited has informed the Exchange about Action(s) initiated or orders passed",
        "amount_cr": "",
        "order_book_cr": "Rs. 6138 Cr",
        "date": "2025-12-17",
        "category": "General",
        "pdf_link": "https://nsearchives.nseindia.com/corporate/STEELCITY_17122025131334_img050.pdf",
        "sentiment": "positive"
    },
    {
        "id": 80,
        "company": "Rulka Electricals Ltd",
        "client": "Undisclosed Client",
        "type": "Order Received",
        "description": "Updates Rulka Electricals Limited has informed the Exchange regarding 'Intimation of confirmed new orders.'. Confirmed new MEP electrical and fire",
        "amount_cr": "",
        "order_book_cr": "Rs. 17198 Cr",
        "date": "2025-12-17",
        "category": "General",
        "pdf_link": "https://nsearchives.nseindia.com/corporate/RULKA_17122025121938_Order.pdf",
        "sentiment": "positive"
    },
    {
        "id": 81,
        "company": "Diamond Power Infrastructure Ltd",
        "client": "Undisclosed Client",
        "type": "Order Received",
        "description": "Announcement under Regulation 30 (LODR)-Award_of_Order_Receipt_of_Order Diamond Power Infrastructure Limited has informed the exchange regarding the",
        "amount_cr": "",
        "order_book_cr": "Rs. 6479 Cr",
        "date": "2025-12-17",
        "category": "Energy",
        "pdf_link": "https://www.bseindia.com/stockinfo/AnnPdfOpen.aspx?Pname=319f6843-b431-4326-bc0a-186d50308d8d.pdf",
        "sentiment": "positive"
    },
    {
        "id": 82,
        "company": "Updater Services Ltd",
        "client": "Chennai Tax Officer dated",
        "type": "Order Received",
        "description": "Listing Obligations and Disclosure Requirements) Regulations - 2015 Updater Services received Rs41.57 lakh GST order from Chennai Tax Officer dated",
        "amount_cr": "Rs41.57 lakh",
        "order_book_cr": "Rs. 46592 Cr",
        "date": "2025-12-17",
        "category": "General",
        "pdf_link": "https://www.bseindia.com/stockinfo/AnnPdfOpen.aspx?Pname=7a4efa10-891f-4dca-b22d-3b0822cacc0f.pdf",
        "sentiment": "positive"
    },
    {
        "id": 83,
        "company": "Larsen & Toubro Ltd",
        "client": "Undisclosed Client",
        "type": "Order Received",
        "description": "Announcement under Regulation 30 (LODR)-Award_of_Order_Receipt_of_Order L&T Wins Orders (Large*) for Buildings & Factories Business Wins large EPC",
        "amount_cr": "",
        "order_book_cr": "Rs. 22060 Cr",
        "date": "2025-12-17",
        "category": "General",
        "pdf_link": "https://www.bseindia.com/stockinfo/AnnPdfOpen.aspx?Pname=e0a47602-755f-40fb-8ea0-0d7f83509c41.pdf",
        "sentiment": "positive"
    },
    {
        "id": 84,
        "company": "Emmforce Autotech Ltd",
        "client": "Undisclosed Client",
        "type": "Order Received",
        "description": "production began 16 Dec 2025 for Rs.470 Cr US export order; first shipment end-December",
        "amount_cr": "Rs.470 Cr",
        "order_book_cr": "Rs. 41794 Cr",
        "date": "2025-12-17",
        "category": "General",
        "pdf_link": "https://www.bseindia.com/stockinfo/AnnPdfOpen.aspx?Pname=127053db-8cf0-437b-9ac3-c7642af315bb.pdf",
        "sentiment": "positive"
    },
    {
        "id": 85,
        "company": "Z-Tech (India) Ltd",
        "client": "Undisclosed Client",
        "type": "Order Received",
        "description": "Press Release Z-Tech (India) Limited has informed the Exchange regarding a press release dated December 17, 2025, titled \"Z-Tech secures order from",
        "amount_cr": "",
        "order_book_cr": "Rs. 69298 Cr",
        "date": "2025-12-17",
        "category": "Technology",
        "pdf_link": "https://nsearchives.nseindia.com/corporate/ZTECH_17122025102512_pressrelease17122025.pdf",
        "sentiment": "positive"
    },
    {
        "id": 86,
        "company": "Suzlon Energy Ltd",
        "client": "Undisclosed Client",
        "type": "Order Received",
        "description": "Announcement under Regulation 30 (LODR)-Press Release / Media Release Suzlon and Yanara extend partnership with 306 MW wind turbine orders in",
        "amount_cr": "",
        "order_book_cr": "Rs. 43405 Cr",
        "date": "2025-12-17",
        "category": "General",
        "pdf_link": "https://www.bseindia.com/stockinfo/AnnPdfOpen.aspx?Pname=834c541e-363e-49d3-9e15-666634da2df7.pdf",
        "sentiment": "positive"
    },
    {
        "id": 87,
        "company": "Varroc Engineering Ltd",
        "client": "Undisclosed Client",
        "type": "Order Received",
        "description": "Powertrain Solutions: 25.8% Lighting Solutions: 17% Aftermarket: 10% E-Mobility: 5.8% HMI Solutions: 3.8% Others (Overseas): 2.5% Order Book Varroc",
        "amount_cr": "",
        "order_book_cr": "Rs. 58722 Cr",
        "date": "2025-12-17",
        "category": "Energy",
        "pdf_link": "/company/id/1274377/",
        "sentiment": "positive"
    },
    {
        "id": 88,
        "company": "Kross Ltd",
        "client": "Tier",
        "type": "Order Received",
        "description": "Others: 2% International Expansion Co. is scaling exports (4.2% of H1FY26 revenue) with purchase orders from Tier-1 OEMs in Europe and the US",
        "amount_cr": "",
        "order_book_cr": "Rs. 46353 Cr",
        "date": "2025-12-17",
        "category": "General",
        "pdf_link": "/company/id/1284971/",
        "sentiment": "positive"
    },
    {
        "id": 89,
        "company": "Usha Martin Ltd",
        "client": "Undisclosed Client",
        "type": "Order Received",
        "description": "worth of assets provisionally attached. An appeal led to a status quo order until November 2024. The CBI also filed an FIR in 2020 alleging attempts",
        "amount_cr": "",
        "order_book_cr": "Rs. 35678 Cr",
        "date": "2025-12-17",
        "category": "General",
        "pdf_link": "/company/id/3574/",
        "sentiment": "positive"
    },
    {
        "id": 90,
        "company": "Logica Infoway Ltd",
        "client": "Middle Eastern distributors",
        "type": "Order Received",
        "description": "facilitating export logistics. It focuses on bulk orders from Middle Eastern distributors. Segment-wise Revenue H1FY26 Distribution: 43.3% Ecommerce",
        "amount_cr": "",
        "order_book_cr": "Rs. 34701 Cr",
        "date": "2025-12-17",
        "category": "General",
        "pdf_link": "/company/id/1275397/",
        "sentiment": "positive"
    },
    {
        "id": 91,
        "company": "Marc Technocrats Ltd",
        "client": "Undisclosed Client",
        "type": "Order Received",
        "description": "Assam, Arunachal Pradesh, etc. Order Book As of 30 September 2025, the company has total ongoing projects worth 401 Crs, of which 145 Crs has been",
        "amount_cr": "rs, ",
        "order_book_cr": "Rs. 49653 Cr",
        "date": "2025-12-17",
        "category": "General",
        "pdf_link": "/company/id/1285826/",
        "sentiment": "positive"
    },
    {
        "id": 92,
        "company": "Frog Innovations Ltd",
        "client": "Undisclosed Client",
        "type": "Order Received",
        "description": "So, whether we have any pilot project or any order or any order in pipeline, any talking with the customers, like any visibility on that? Konark",
        "amount_cr": "rs, ",
        "order_book_cr": "Rs. 16726 Cr",
        "date": "2025-12-17",
        "category": "General",
        "pdf_link": "https://nsearchives.nseindia.com/corporate/FROGCELLSAT_17122025130254_Disclosure_of_Transcript_signed.pdf",
        "sentiment": "positive"
    },
    {
        "id": 93,
        "company": "Tata Consultancy Services Ltd",
        "client": "Undisclosed Client",
        "type": "Order Received",
        "description": "personnel trained in AI 180,000 Employees with higher order skills >281,000 World\u2019s largest hackathon 14 AI Awards (LTM) 8/8 \u2018Leadership",
        "amount_cr": "",
        "order_book_cr": "Rs. 37017 Cr",
        "date": "2025-12-17",
        "category": "General",
        "pdf_link": "https://www.bseindia.com/stockinfo/AnnPdfOpen.aspx?Pname=0d9ed3a7-0106-4b36-840e-ef76c59a3c7a.pdf",
        "sentiment": "positive"
    },
    {
        "id": 94,
        "company": "Rajputana Biodiesel Ltd",
        "client": "Undisclosed Client",
        "type": "Order Received",
        "description": "Bagging/Receiving of orders/contracts Rajputana Biodiesel Limited has informed the Exchange about Bagging/Receiving of orders/contracts Received",
        "amount_cr": "",
        "order_book_cr": "Rs. 65667 Cr",
        "date": "2025-12-16",
        "category": "General",
        "pdf_link": "https://nsearchives.nseindia.com/corporate/RBPL_16122025230052_Rajputana_LOIsigned.pdf",
        "sentiment": "positive"
    },
    {
        "id": 95,
        "company": "Rail Vikas Nigam Ltd",
        "client": "Undisclosed Client",
        "type": "Order Received",
        "description": "Announcement under Regulation 30 (LODR)-Award_of_Order_Receipt_of_Order Disclosure under Regulation 30 of SEBI (LODR) Regulations, 2015- Receipt of",
        "amount_cr": "",
        "order_book_cr": "Rs. 59959 Cr",
        "date": "2025-12-16",
        "category": "General",
        "pdf_link": "https://www.bseindia.com/stockinfo/AnnPdfOpen.aspx?Pname=d28cca84-1bc6-43df-b36d-56770fbecdc7.pdf",
        "sentiment": "positive"
    },
    {
        "id": 96,
        "company": "Zenlabs Ethica Ltd",
        "client": "Undisclosed Client",
        "type": "Order Received",
        "description": "of these facilities, the minimum order quantity offered is 2000 boxes of drugs. c) The company is also into private label manufacturing of different",
        "amount_cr": "",
        "order_book_cr": "Rs. 25471 Cr",
        "date": "2025-12-16",
        "category": "Pharmaceuticals",
        "pdf_link": "/company/id/2228/",
        "sentiment": "positive"
    },
    {
        "id": 97,
        "company": "Max Heights Infrastructure Ltd",
        "client": "Undisclosed Client",
        "type": "Regulatory Order/Penalty",
        "description": "ceased to be the subsidiary company of MHIL on December 30th, 2023. SEBI Penalty Order: SEBI\u2019s Adjudicating Officer has issued a final order dated",
        "amount_cr": "",
        "order_book_cr": "Rs. 13767 Cr",
        "date": "2025-12-16",
        "category": "General",
        "pdf_link": "/company/id/7314/",
        "sentiment": "negative"
    },
    {
        "id": 98,
        "company": "Silicon Rental Solutions Ltd",
        "client": "Undisclosed Client",
        "type": "Order Received",
        "description": "Announcement under Regulation 30 (LODR)-Award_of_Order_Receipt_of_Order Disclosure under Regulation 30 of SEBI (Listing Obligations and Disclosure",
        "amount_cr": "",
        "order_book_cr": "Rs. 29926 Cr",
        "date": "2025-12-16",
        "category": "General",
        "pdf_link": "https://www.bseindia.com/stockinfo/AnnPdfOpen.aspx?Pname=0af6fee7-f8c1-44f4-ba5b-858f7be041c8.pdf",
        "sentiment": "positive"
    },
    {
        "id": 99,
        "company": "Tirth Plastic Ltd",
        "client": "Undisclosed Client",
        "type": "Order Received",
        "description": "significant movement in price, in order to ensure that investors have latest relevant information about the company and to inform the market so that",
        "amount_cr": "",
        "order_book_cr": "Rs. 53704 Cr",
        "date": "2025-12-16",
        "category": "General",
        "pdf_link": "/company/id/1269407/",
        "sentiment": "positive"
    },
    {
        "id": 100,
        "company": "Triumph International Finance India Ltd",
        "client": "Undisclosed Client",
        "type": "Order Received",
        "description": "on December 16, 2025 with reference to significant movement in price, in order to ensure that investors have latest relevant information about the",
        "amount_cr": "",
        "order_book_cr": "Rs. 79015 Cr",
        "date": "2025-12-16",
        "category": "General",
        "pdf_link": "/company/id/1270147/",
        "sentiment": "positive"
    },
    {
        "id": 101,
        "company": "Valiant Communications Ltd",
        "client": "Undisclosed Client",
        "type": "Order Received",
        "description": "reference to significant movement in price, in order to ensure that investors have latest relevant information about the company and to inform the",
        "amount_cr": "",
        "order_book_cr": "Rs. 34252 Cr",
        "date": "2025-12-16",
        "category": "General",
        "pdf_link": "/company/id/3594/",
        "sentiment": "positive"
    },
    {
        "id": 102,
        "company": "Mansi Finance (Chennai) Ltd",
        "client": "Undisclosed Client",
        "type": "Order Received",
        "description": "with reference to significant movement in price, in order to ensure that investors have latest relevant information about the company and to inform",
        "amount_cr": "",
        "order_book_cr": "Rs. 39993 Cr",
        "date": "2025-12-16",
        "category": "General",
        "pdf_link": "/company/id/2002/",
        "sentiment": "positive"
    },
    {
        "id": 103,
        "company": "Concord Enviro Systems Ltd",
        "client": "Undisclosed Client",
        "type": "Order Received",
        "description": "reference to significant movement in price, in order to ensure that investors have latest relevant information about the company and to inform the",
        "amount_cr": "",
        "order_book_cr": "Rs. 13551 Cr",
        "date": "2025-12-16",
        "category": "General",
        "pdf_link": "/company/id/1285203/",
        "sentiment": "positive"
    },
    {
        "id": 104,
        "company": "Digjam Ltd",
        "client": "Undisclosed Client",
        "type": "Order Received",
        "description": "movement in price, in order to ensure that investors have latest relevant information about the company and to inform the market so that the interest",
        "amount_cr": "",
        "order_book_cr": "Rs. 73570 Cr",
        "date": "2025-12-16",
        "category": "General",
        "pdf_link": "/company/id/1273414/",
        "sentiment": "positive"
    },
    {
        "id": 105,
        "company": "Coromandel Engineering Company Ltd",
        "client": "Undisclosed Client",
        "type": "Order Received",
        "description": "December 16, 2025 with reference to significant movement in price, in order to ensure that investors have latest relevant information about the",
        "amount_cr": "",
        "order_book_cr": "Rs. 9698 Cr",
        "date": "2025-12-16",
        "category": "General",
        "pdf_link": "/company/id/714/",
        "sentiment": "positive"
    },
    {
        "id": 106,
        "company": "Maha Rashtra Apex Corporation Ltd",
        "client": "Undisclosed Client",
        "type": "Order Received",
        "description": "16, 2025 with reference to significant movement in price, in order to ensure that investors have latest relevant information about the company and to",
        "amount_cr": "",
        "order_book_cr": "Rs. 13285 Cr",
        "date": "2025-12-16",
        "category": "General",
        "pdf_link": "/company/id/1957/",
        "sentiment": "positive"
    },
    {
        "id": 107,
        "company": "Anna Infrastructures Ltd",
        "client": "Undisclosed Client",
        "type": "Order Received",
        "description": "reference to significant movement in price, in order to ensure that investors have latest relevant information about the company and to inform the",
        "amount_cr": "",
        "order_book_cr": "Rs. 9902 Cr",
        "date": "2025-12-16",
        "category": "General",
        "pdf_link": "/company/id/201/",
        "sentiment": "positive"
    },
    {
        "id": 108,
        "company": "Transformers & Rectifiers India Ltd",
        "client": "Undisclosed Client",
        "type": "Order Received",
        "description": "on December 16, 2025 with reference to significant movement in price, in order to ensure that investors have latest relevant information about the",
        "amount_cr": "",
        "order_book_cr": "Rs. 69423 Cr",
        "date": "2025-12-16",
        "category": "General",
        "pdf_link": "/company/id/3458/",
        "sentiment": "positive"
    },
    {
        "id": 109,
        "company": "Aerpace Industries Ltd",
        "client": "Undisclosed Client",
        "type": "Order Received",
        "description": "reference to significant movement in price, in order to ensure that investors have latest relevant information about the company and to inform the",
        "amount_cr": "",
        "order_book_cr": "Rs. 59327 Cr",
        "date": "2025-12-16",
        "category": "General",
        "pdf_link": "/company/id/212090/",
        "sentiment": "positive"
    },
    {
        "id": 110,
        "company": "Denta Water & Infra Solutions Ltd",
        "client": "Undisclosed Client",
        "type": "Order Received",
        "description": "Amid Strong Financial Turnaround Abakkus' Sunil Singhania acquired 1.3% (~Rs12.2cr) in Denta; strong FY25 turnaround, Rs720cr order book",
        "amount_cr": "Rs12.2cr",
        "order_book_cr": "Rs. 11678 Cr",
        "date": "2025-12-16",
        "category": "General",
        "pdf_link": "https://www.bseindia.com/stockinfo/AnnPdfOpen.aspx?Pname=04e1bbd8-c5ca-4732-b523-cd6752bfd164.pdf",
        "sentiment": "positive"
    },
    {
        "id": 111,
        "company": "Jain Resource Recycling Ltd",
        "client": "Undisclosed Client",
        "type": "Regulatory Order/Penalty",
        "description": "Announcement under Regulation 30 (LODR)-Award_of_Order_Receipt_of_Order Imposition of penalty on Mr. Kamlesh Jain, Promoter of the Company & Jain",
        "amount_cr": "",
        "order_book_cr": "Rs. 47101 Cr",
        "date": "2025-12-16",
        "category": "General",
        "pdf_link": "https://www.bseindia.com/stockinfo/AnnPdfOpen.aspx?Pname=22b3c3bf-424a-46e9-92ff-a157edaff1cd.pdf",
        "sentiment": "negative"
    },
    {
        "id": 112,
        "company": "Nagarjuna Fertilizers & Chemicals Ltd",
        "client": "Undisclosed Client",
        "type": "Regulatory Order/Penalty",
        "description": "Company wish to update the status of Litigation. Telangana HC interim order Dec 10, 2025: provisional attachment of bank accounts > Rs.7 crore in",
        "amount_cr": "Rs.7 crore",
        "order_book_cr": "Rs. 11514 Cr",
        "date": "2025-12-16",
        "category": "General",
        "pdf_link": "https://www.bseindia.com/stockinfo/AnnPdfOpen.aspx?Pname=6417dcc6-ff39-425d-b942-3ca7f16d1521.pdf",
        "sentiment": "negative"
    },
    {
        "id": 113,
        "company": "Atishay Ltd",
        "client": "The Udaipur Central Co",
        "type": "Order Received",
        "description": "Announcement under Regulation 30 (LODR)-Award_of_Order_Receipt_of_Order The Company has been awarded a Work Order from The Udaipur Central Co",
        "amount_cr": "",
        "order_book_cr": "Rs. 43039 Cr",
        "date": "2025-12-16",
        "category": "General",
        "pdf_link": "https://www.bseindia.com/stockinfo/AnnPdfOpen.aspx?Pname=2c5c4f42-b433-4924-8f6b-70ce7d5b96e5.pdf",
        "sentiment": "positive"
    },
    {
        "id": 114,
        "company": "Railtel Corporation of India Ltd",
        "client": "Undisclosed Client",
        "type": "Order Received",
        "description": "Announcement under Regulation 30 (LODR)-Award_of_Order_Receipt_of_Order New Order Received",
        "amount_cr": "",
        "order_book_cr": "Rs. 43061 Cr",
        "date": "2025-12-16",
        "category": "General",
        "pdf_link": "https://www.bseindia.com/stockinfo/AnnPdfOpen.aspx?Pname=4d95dae5-0b07-4e94-ada8-c077615e5181.pdf",
        "sentiment": "positive"
    },
    {
        "id": 115,
        "company": "Canara HSBC Life Insurance Company Ltd",
        "client": "Undisclosed Client",
        "type": "Regulatory Order/Penalty",
        "description": "Announcement Under Clause 20 Of The Para A Of Part A Of The Regulation 30 Of The SEBI (LODR) Regulations, 2015-GST Demand Order In Uttar Pradesh State",
        "amount_cr": "",
        "order_book_cr": "Rs. 18451 Cr",
        "date": "2025-12-16",
        "category": "General",
        "pdf_link": "https://www.bseindia.com/stockinfo/AnnPdfOpen.aspx?Pname=197af11b-48b7-4601-b1b9-1f067204890c.pdf",
        "sentiment": "negative"
    },
    {
        "id": 116,
        "company": "Max India Ltd",
        "client": "Undisclosed Client",
        "type": "Order Received",
        "description": "Receipt Of RD Order For Change In Registered Office As per detailed disclosure enclosed. RD order dated Dec 12, 2025 approved shift of Max India",
        "amount_cr": "",
        "order_book_cr": "Rs. 40512 Cr",
        "date": "2025-12-16",
        "category": "General",
        "pdf_link": "https://www.bseindia.com/stockinfo/AnnPdfOpen.aspx?Pname=0cc0e76f-9daa-432f-887e-58d54a28149f.pdf",
        "sentiment": "positive"
    },
    {
        "id": 117,
        "company": "Shree Refrigerations Ltd",
        "client": "Undisclosed Client",
        "type": "Order Received",
        "description": "Announcement under Regulation 30 (LODR)-Award_of_Order_Receipt_of_Order Pursuant to the provisions of Regulation 30 read with Sub-para 4, Para B",
        "amount_cr": "",
        "order_book_cr": "Rs. 26421 Cr",
        "date": "2025-12-16",
        "category": "General",
        "pdf_link": "https://www.bseindia.com/stockinfo/AnnPdfOpen.aspx?Pname=f0ec8c00-0636-4107-a780-2cc914d86a66.pdf",
        "sentiment": "positive"
    },
    {
        "id": 118,
        "company": "Wework India Management Ltd",
        "client": "Undisclosed Client",
        "type": "Regulatory Order/Penalty",
        "description": "Disclosure under Regulation 30 of SEBI Listing Regulations GST order (Dec 11, 2025): disallowed ITC INR8.14cr; interest INR6.43cr; penalty INR0.81cr",
        "amount_cr": "INR8.14cr",
        "order_book_cr": "Rs. 73078 Cr",
        "date": "2025-12-16",
        "category": "General",
        "pdf_link": "https://www.bseindia.com/stockinfo/AnnPdfOpen.aspx?Pname=5e90517a-eded-41a2-9218-c86f37cc7332.pdf",
        "sentiment": "negative"
    },
    {
        "id": 119,
        "company": "Z-Tech (India) Ltd",
        "client": "Undisclosed Client",
        "type": "Order Received",
        "description": "in Value Discovery Summit on 16 Dec 2025; presented FY25 revenue \u20b994.4Cr, EBITDA \u20b927.8Cr, order book ~\u20b9200Cr",
        "amount_cr": "",
        "order_book_cr": "Rs. 73722 Cr",
        "date": "2025-12-16",
        "category": "General",
        "pdf_link": "https://nsearchives.nseindia.com/corporate/ZTECH_16122025173237_intimation16122025.pdf",
        "sentiment": "positive"
    }
]